mapy/__init__.py
mapy/base.py
mapy/multiple_columns.py
mapy/single_column.py
mapy/tests/__init__.py
mapy/tests/test_multiple_columns.py
mapy/tests/test_single_column.py
mapy/utils/__init__.py
mapy/utils/utils.py
mapy_data_qa-0.0.4.dist-info/METADATA
mapy_data_qa-0.0.4.dist-info/WHEEL
mapy_data_qa-0.0.4.dist-info/top_level.txt
mapy_data_qa-0.0.4.dist-info/RECORD
