Metadata-Version: 2.1
Name: mapy-data-qa
Version: 0.0.4
Summary: UNKNOWN
Home-page: UNKNOWN
Author: Bigabid
Author-email: tech@bigabid.com
License: MIT
Platform: UNKNOWN
Requires-Python: >=3.6
Requires-Dist: pandas
Requires-Dist: pytest
Requires-Dist: numpy
